pyenlone/__init__.py
pyenlone/_proxy.py
pyenlone/enloneexception.py
pyenlone/tasks/__init__.py
pyenlone/tasks/operation.py
pyenlone/tasks/task.py
pyenlone/v/__init__.py
pyenlone/v/_apikey.py
pyenlone/v/_oauth.py
pyenlone/v/agent.py
pyenlone/v/detail_agent.py
pyenlone/v/team.py
pyenlone/v/team_member.py
pyenlone-0.2.0.dist-info/LICENSE
pyenlone-0.2.0.dist-info/METADATA
pyenlone-0.2.0.dist-info/WHEEL
pyenlone-0.2.0.dist-info/top_level.txt
pyenlone-0.2.0.dist-info/RECORD
