Metadata-Version: 2.1
Name: pyenlone
Version: 0.2.0
Summary: A python implementation of enl.one API
Home-page: https://gitlab.com/potato-tools/pyenlone
Author: QuanticPotato
License: UNKNOWN
Platform: UNKNOWN
Classifier: Programming Language :: Python :: 3
Classifier: License :: OSI Approved :: MIT License
Classifier: Operating System :: OS Independent
Requires-Dist: requests (>=2.4)
Requires-Dist: requests-cache
